seriesmanagementsystem-1.3.1.dist-info/licenses/LICENSE.rst
seriesmgmtsystem/__init__.py
seriesmgmtsystem/data/bibdb.bib
seriesmgmtsystem/data/captionnames.tex
seriesmgmtsystem/data/lecture.cfg
seriesmgmtsystem/data/sms.sty
seriesmgmtsystem/etc/lecture.cfg
seriesmgmtsystem/etc/logging.yaml
seriesmgmtsystem/etc/serieManagementSystem-completion.bash
seriesmgmtsystem/etc/seriesmgmtsystem.conf
seriesmgmtsystem/main/__init__.py
seriesmgmtsystem/main/__main__.py
seriesmgmtsystem/main/main.py
seriesmgmtsystem/main/mainImpl.py
seriesmgmtsystem/sms/__init__.py
seriesmgmtsystem/sms/serieManagementSystem.py
seriesmgmtsystem/utils/LaTeX.py
seriesmgmtsystem/utils/Utils.py
seriesmgmtsystem/utils/ZipUtils.py
seriesmgmtsystem/utils/__init__.py
seriesmanagementsystem-1.3.1.dist-info/METADATA
seriesmanagementsystem-1.3.1.dist-info/WHEEL
seriesmanagementsystem-1.3.1.dist-info/entry_points.txt
seriesmanagementsystem-1.3.1.dist-info/top_level.txt
seriesmanagementsystem-1.3.1.dist-info/RECORD
